setup.py
example/__init__.py
example/fabfile.py
example/config/__init__.py
example/config/settings.py
fabricator/__init__.py
fabricator/config.py
fabricator/targets.py
fabricator.egg-info/PKG-INFO
fabricator.egg-info/SOURCES.txt
fabricator.egg-info/dependency_links.txt
fabricator.egg-info/not-zip-safe
fabricator.egg-info/top_level.txt
tests/__init__.py
tests/test_config.py
tests/test_project/__init__.py
tests/test_project/test_config.py