Metadata-Version: 1.1
Name: fabricator
Version: 0.1.28
Summary: Multi user configuration and default fabric targets for you python project
Home-page: https://github.com/SevenQuark/fabricator
Author: SevenQuark
Author-email: info@sevenquark.com
License: MIT license
Platform: UNKNOWN
Classifier: Development Status :: 3 - Alpha
Classifier: Environment :: Web Environment
Classifier: Intended Audience :: Developers
Classifier: License :: OSI Approved :: MIT License
Classifier: Programming Language :: Python
Classifier: Programming Language :: Python :: 2
Classifier: Programming Language :: Python :: 2.6
Classifier: Programming Language :: Python :: 2.7
Classifier: Topic :: Software Development :: Libraries :: Python Modules
Requires: Fabric (>= 1.4)
